justifier/__init__.py
justifier/cli.py
justifier/context.py
justifier/justifier.py
justifier/utils.py
text_justifier-0.10.0.dist-info/LICENSE
text_justifier-0.10.0.dist-info/METADATA
text_justifier-0.10.0.dist-info/WHEEL
text_justifier-0.10.0.dist-info/entry_points.txt
text_justifier-0.10.0.dist-info/top_level.txt
text_justifier-0.10.0.dist-info/RECORD
