Metadata-Version: 2.1
Name: text-justifier
Version: 0.10.0
Summary: Justify and hyphenate text in files and/or standard input
Home-page: https://github.com/unixnut/Python-Text-Justifier
Author: Alastair Irvine
Author-email: alastair@plug.org.au
License: GNU General Public License v3
Keywords: justifier,text formatting
Platform: UNKNOWN
Classifier: Development Status :: 2 - Pre-Alpha
Classifier: Intended Audience :: Developers
Classifier: License :: OSI Approved :: GNU General Public License v3 (GPLv3)
Classifier: Natural Language :: English
Classifier: Programming Language :: Python :: 3
Classifier: Programming Language :: Python :: 3.5
Classifier: Programming Language :: Python :: 3.6
Classifier: Programming Language :: Python :: 3.7
Classifier: Programming Language :: Python :: 3.8
Requires-Python: >=3.5
Requires-Dist: Click (>=7.0)
Requires-Dist: pyphen (>=0.10.0)
